synapse_uploader/__init__.py
synapse_uploader/_version.py
synapse_uploader/cli.py
synapse_uploader/synapse_uploader.py
synapse_uploader/utils.py
synapse_uploader-0.0.6.dist-info/LICENSE
synapse_uploader-0.0.6.dist-info/METADATA
synapse_uploader-0.0.6.dist-info/NOTICE
synapse_uploader-0.0.6.dist-info/WHEEL
synapse_uploader-0.0.6.dist-info/entry_points.txt
synapse_uploader-0.0.6.dist-info/top_level.txt
synapse_uploader-0.0.6.dist-info/RECORD
