Metadata-Version: 2.1
Name: synapse-uploader
Version: 0.0.6
Summary: Utility to upload a directory and files to Synapse.
Home-page: https://github.com/ki-tools/synapse_uploader
Author: Patrick Stout
Author-email: pstout@prevagroup.com
License: Apache2
Classifier: Programming Language :: Python
Classifier: Programming Language :: Python :: 3.10
Classifier: Programming Language :: Python :: 3.11
Classifier: License :: OSI Approved :: Apache Software License
Classifier: Operating System :: OS Independent
License-File: LICENSE
License-File: NOTICE
Requires-Dist: synapseclient <3.0.0,>=2.3.1
Requires-Dist: synapsis >=0.0.6
